Workbook

Sheet LEEME
A1: MODELO ECONÓMICO — GOOGLE ADS · D-CODE PARTNERS (18/09/2026)
A3: Este libro NO es una previsión. Son escenarios matemáticos para entender la economía del canal.
A4: Texto AZUL = dato de entrada editable. Relleno AMARILLO = supuesto clave que hay que sustituir por un dato MEDIDO.
A5: Texto negro = fórmula. Texto verde = referencia a otra hoja.
A6: Etiquetas: [FUENTE] dato citado · [HIPÓTESIS] supuesto sin medir · [DECISIÓN] regla de negocio que decide Dirección.
A7: Precios: PRICING OFICIAL de Notion (19/08/2026). OJO: los criterios de pricing del 18/09/2026 prohíben paquetes tipo Basic/Pro;
A8: hay que reconciliar ambos antes de cotizar. Aquí se usan solo como referencia de ticket.
A9: Coste interno: 20 €/h [FUENTE: decisión de Dirección 18/09/2026].
A10: Horas de implantación, horas mensuales e infraestructura: [HIPÓTESIS] — NO MEDIDO. Sustituir por horas reales registradas.
A11: Modelo 3 (30 días de prueba sin factura): el coste de las pruebas que NO se convierten se imputa como coste de adquisición.
A13: Hojas: Supuestos · Contribucion · Embudo · Umbrales · Oferta400
A14: Cómo usar: 1) cambia el producto en Supuestos!C4 2) sustituye amarillos por datos reales 3) lee Embudo y Umbrales.

Sheet Supuestos
A1: SUPUESTOS
A3: Coste interno (€/h) | C3: 20 | D3: [FUENTE] Dirección 18/09/2026
A4: Producto seleccionado (1-3) | C4: 3 | D4: 1=Automatización Básica · 2=Soporte IA Starter · 3=Comercial IA núcleo
A5: Meses de relación considerados | C5: 12 | D5: [HIPÓTESIS] retención NO MEDIDA (sin histórico de clientes suficiente)
A6: Fracción de la contribución admisible para adquisición (α) | C6: 0.5 | D6: [DECISIÓN] regla de negocio: la decide Dirección
A8: Producto | B8: ID | C8: Implantación (€) | D8: Mensualidad (€/mes) | E8: Horas implantación | F8: Horas/mes servicio | G8: Infra €/mes | H8: Fuente precio
A9: Automatización Básica | B9: 1 | C9: 800 | D9: 130 | E9: 15 | F9: 2 | G9: 20 | H9: [FUENTE] Notion · PRICING OFICIAL 19/08/2026 (vendible ahora). Horas e infra: [HIPÓTESIS]
A10: Soporte IA Starter (Tickets IA) | B10: 2 | C10: 1600 | D10: 190 | E10: 35 | F10: 3 | G10: 20 | H10: [FUENTE] Notion · PRICING OFICIAL 19/08/2026 (vendible ahora). Horas e infra: [HIPÓTESIS]
A11: Comercial IA núcleo | B11: 3 | C11: 2600 | D11: 280 | E11: 50 | F11: 4 | G11: 20 | H11: [FUENTE] Notion · PRICING OFICIAL 19/08/2026 (vendible ahora). Horas e infra: [HIPÓTESIS]
A13: Horas comerciales por etapa | C13: Horas | D13: Nota
A14: Triaje por lead | C14: 0.25 | D14: [HIPÓTESIS]
A15: Reunión/diagnóstico celebrado (prep+reunión+notas) | C15: 1.5 | D15: [HIPÓTESIS]
A16: Propuesta preparada | C16: 2 | D16: [HIPÓTESIS] el generador de propuestas reduce esto
A18: Palanca del escenario | C18: X desfavorable | D18: Y intermedio | E18: Z favorable | F18: Referencia externa
A19: CPC medio (€) | C19: 4 | D19: 2.5 | E19: 1.5 | F19: [FUENTE] EE.UU. Business Services 2026 mediana 5,87 $ (WordStream/LocaliQ). España: estimaciones de terceros 0,40–4 € (adberg/Ahrefs 2026). Keywords concretas: NO MEDIDO
A20: CTR | C20: 0.03 | D20: 0.05 | E20: 0.08 | F20: [FUENTE] EE.UU. Business Services 2026 mediana 6,10 %
A21: Conversión clic→lead (landing) | C21: 0.02 | D21: 0.05 | E21: 0.08 | F21: [FUENTE] EE.UU. Business Services 2026 4,85 %; Unbounce Professional Services mediana 6,1 % (todas las fuentes de tráfico)
A22: Lead→lead válido | C22: 0.5 | D22: 0.65 | E22: 0.75 | F22: [FUENTE parcial] Chili Piper 2024: 14,1 % de envíos B2B descartados. Aquí más conservador. [HIPÓTESIS]
A23: Válido→reunión celebrada | C23: 0.4 | D23: 0.6 | E23: 0.7 | F23: [HIPÓTESIS] NO MEDIDO en D-Code
A24: Reunión→propuesta | C24: 0.5 | D24: 0.65 | E24: 0.75 | F24: [HIPÓTESIS] NO MEDIDO
A25: Propuesta→inicio prueba 30 días | C25: 0.3 | D25: 0.5 | E25: 0.6 | F25: [HIPÓTESIS] NO MEDIDO
A26: Prueba→cliente que paga | C26: 0.5 | D26: 0.7 | E26: 0.8 | F26: [HIPÓTESIS] NO MEDIDO — palanca más sensible del Modelo 3
A28: Tasa lead→cliente (resultado) | C28: =C22*C23*C24*C25*C26 -> 0.015 | D28: =D22*D23*D24*D25*D26 -> 0.088725 | E28: =E22*E23*E24*E25*E26 -> 0.189
A30: Producto activo | C30: =INDEX(A9:A11,$C$4) -> Comercial IA núcleo
A31: Implantación activa | C31: =INDEX(C9:C11,$C$4) -> 2600
A32: Mensualidad activa | C32: =INDEX(D9:D11,$C$4) -> 280
A33: Horas implantación activas | C33: =INDEX(E9:E11,$C$4) -> 50
A34: Horas/mes activas | C34: =INDEX(F9:F11,$C$4) -> 4
A35: Infra activa | C35: =INDEX(G9:G11,$C$4) -> 20

Sheet Contribucion
A1: CONTRIBUCIÓN POR CLIENTE Y CAC MÁXIMO
A3: Producto | B3: Margen implantación (€) | C3: Contribución mensual (€) | D3: Contribución en N meses (€) | E3: CAC máx. equilibrio (€) | F3: CAC máx. con α (€) | G3: Meses para recuperar CAC α tras implantación
A4: =Supuestos!A9 -> Automatización Básica | B4: =Supuestos!C9-Supuestos!E9*Supuestos!$C$3 -> 500 | C4: =Supuestos!D9-Supuestos!F9*Supuestos!$C$3-Supuestos!G9 -> 70 | D4: =B4+C4*Supuestos!$C$5 -> 1340 | E4: =D4 -> 1340 | F4: =D4*Supuestos!$C$6 -> 670 | G4: =IF(F4<=B4,0,IF(C4<=0,"nunca",(F4-B4)/C4)) -> 2.4285714
A5: =Supuestos!A10 -> Soporte IA Starter (Tickets IA) | B5: =Supuestos!C10-Supuestos!E10*Supuestos!$C$3 -> 900 | C5: =Supuestos!D10-Supuestos!F10*Supuestos!$C$3-Supuestos!G10 -> 110 | D5: =B5+C5*Supuestos!$C$5 -> 2220 | E5: =D5 -> 2220 | F5: =D5*Supuestos!$C$6 -> 1110 | G5: =IF(F5<=B5,0,IF(C5<=0,"nunca",(F5-B5)/C5)) -> 1.9090909
A6: =Supuestos!A11 -> Comercial IA núcleo | B6: =Supuestos!C11-Supuestos!E11*Supuestos!$C$3 -> 1600 | C6: =Supuestos!D11-Supuestos!F11*Supuestos!$C$3-Supuestos!G11 -> 180 | D6: =B6+C6*Supuestos!$C$5 -> 3760 | E6: =D6 -> 3760 | F6: =D6*Supuestos!$C$6 -> 1880 | G6: =IF(F6<=B6,0,IF(C6<=0,"nunca",(F6-B6)/C6)) -> 1.5555556
A8: Fórmula: contribución = (implantación − horas×20) + (mensualidad − horas/mes×20 − infra) × meses. CAC máx. equilibrio = contribución (beneficio 0). CAC máx. con α = contribución × α [DECISIÓN].
A9: Payback: con Modelo 3 la implantación se factura al día 30 si el cliente continúa; si el margen de implantación cubre el CAC, el payback llega con esa primera factura (0 meses adicionales).

Sheet Embudo
A1: EMBUDO POR PRESUPUESTO Y ESCENARIO (producto activo en Supuestos!C4)
A2: ="Producto: "&Supuestos!C30 -> Producto: Comercial IA núcleo
B3: 100 € · X | C3: 100 € · Y | D3: 100 € · Z | E3: 400 € · X | F3: 400 € · Y | G3: 400 € · Z | H3: 800 € · X | I3: 800 € · Y | J3: 800 € · Z
A4: Presupuesto (€) | B4: 100 | C4: 100 | D4: 100 | E4: 400 | F4: 400 | G4: 400 | H4: 800 | I4: 800 | J4: 800
A5: Clics | B5: =B4/Supuestos!C19 -> 25 | C5: =C4/Supuestos!D19 -> 40 | D5: =D4/Supuestos!E19 -> 66.666667 | E5: =E4/Supuestos!C19 -> 100 | F5: =F4/Supuestos!D19 -> 160 | G5: =G4/Supuestos!E19 -> 266.66667 | H5: =H4/Supuestos!C19 -> 200 | I5: =I4/Supuestos!D19 -> 320 | J5: =J4/Supuestos!E19 -> 533.33333
A6: Impresiones | B6: =B5/Supuestos!C20 -> 833.33333 | C6: =C5/Supuestos!D20 -> 800 | D6: =D5/Supuestos!E20 -> 833.33333 | E6: =E5/Supuestos!C20 -> 3333.3333 | F6: =F5/Supuestos!D20 -> 3200 | G6: =G5/Supuestos!E20 -> 3333.3333 | H6: =H5/Supuestos!C20 -> 6666.6667 | I6: =I5/Supuestos!D20 -> 6400 | J6: =J5/Supuestos!E20 -> 6666.6667
A7: Leads | B7: =B5*Supuestos!C21 -> 0.5 | C7: =C5*Supuestos!D21 -> 2 | D7: =D5*Supuestos!E21 -> 5.3333333 | E7: =E5*Supuestos!C21 -> 2 | F7: =F5*Supuestos!D21 -> 8 | G7: =G5*Supuestos!E21 -> 21.333333 | H7: =H5*Supuestos!C21 -> 4 | I7: =I5*Supuestos!D21 -> 16 | J7: =J5*Supuestos!E21 -> 42.666667
A8: Leads válidos | B8: =B7*Supuestos!C22 -> 0.25 | C8: =C7*Supuestos!D22 -> 1.3 | D8: =D7*Supuestos!E22 -> 4 | E8: =E7*Supuestos!C22 -> 1 | F8: =F7*Supuestos!D22 -> 5.2 | G8: =G7*Supuestos!E22 -> 16 | H8: =H7*Supuestos!C22 -> 2 | I8: =I7*Supuestos!D22 -> 10.4 | J8: =J7*Supuestos!E22 -> 32
A9: Reuniones celebradas | B9: =B8*Supuestos!C23 -> 0.1 | C9: =C8*Supuestos!D23 -> 0.78 | D9: =D8*Supuestos!E23 -> 2.8 | E9: =E8*Supuestos!C23 -> 0.4 | F9: =F8*Supuestos!D23 -> 3.12 | G9: =G8*Supuestos!E23 -> 11.2 | H9: =H8*Supuestos!C23 -> 0.8 | I9: =I8*Supuestos!D23 -> 6.24 | J9: =J8*Supuestos!E23 -> 22.4
A10: Propuestas | B10: =B9*Supuestos!C24 -> 0.05 | C10: =C9*Supuestos!D24 -> 0.507 | D10: =D9*Supuestos!E24 -> 2.1 | E10: =E9*Supuestos!C24 -> 0.2 | F10: =F9*Supuestos!D24 -> 2.028 | G10: =G9*Supuestos!E24 -> 8.4 | H10: =H9*Supuestos!C24 -> 0.4 | I10: =I9*Supuestos!D24 -> 4.056 | J10: =J9*Supuestos!E24 -> 16.8
A11: Pruebas iniciadas | B11: =B10*Supuestos!C25 -> 0.015 | C11: =C10*Supuestos!D25 -> 0.2535 | D11: =D10*Supuestos!E25 -> 1.26 | E11: =E10*Supuestos!C25 -> 0.06 | F11: =F10*Supuestos!D25 -> 1.014 | G11: =G10*Supuestos!E25 -> 5.04 | H11: =H10*Supuestos!C25 -> 0.12 | I11: =I10*Supuestos!D25 -> 2.028 | J11: =J10*Supuestos!E25 -> 10.08
A12: Clientes que pagan | B12: =B11*Supuestos!C26 -> 0.0075 | C12: =C11*Supuestos!D26 -> 0.17745 | D12: =D11*Supuestos!E26 -> 1.008 | E12: =E11*Supuestos!C26 -> 0.03 | F12: =F11*Supuestos!D26 -> 0.7098 | G12: =G11*Supuestos!E26 -> 4.032 | H12: =H11*Supuestos!C26 -> 0.06 | I12: =I11*Supuestos!D26 -> 1.4196 | J12: =J11*Supuestos!E26 -> 8.064
A13: CPL (€) | B13: =IFERROR(B4/B7,"-") -> 200 | C13: =IFERROR(C4/C7,"-") -> 50 | D13: =IFERROR(D4/D7,"-") -> 18.75 | E13: =IFERROR(E4/E7,"-") -> 200 | F13: =IFERROR(F4/F7,"-") -> 50 | G13: =IFERROR(G4/G7,"-") -> 18.75 | H13: =IFERROR(H4/H7,"-") -> 200 | I13: =IFERROR(I4/I7,"-") -> 50 | J13: =IFERROR(J4/J7,"-") -> 18.75
A14: Coste por reunión (€) | B14: =IFERROR(B4/B9,"-") -> 1000 | C14: =IFERROR(C4/C9,"-") -> 128.20513 | D14: =IFERROR(D4/D9,"-") -> 35.714286 | E14: =IFERROR(E4/E9,"-") -> 1000 | F14: =IFERROR(F4/F9,"-") -> 128.20513 | G14: =IFERROR(G4/G9,"-") -> 35.714286 | H14: =IFERROR(H4/H9,"-") -> 1000 | I14: =IFERROR(I4/I9,"-") -> 128.20513 | J14: =IFERROR(J4/J9,"-") -> 35.714286
A15: CAC solo anuncios (€) | B15: =IFERROR(B4/B12,"-") -> 13333.333 | C15: =IFERROR(C4/C12,"-") -> 563.53903 | D15: =IFERROR(D4/D12,"-") -> 99.206349 | E15: =IFERROR(E4/E12,"-") -> 13333.333 | F15: =IFERROR(F4/F12,"-") -> 563.53903 | G15: =IFERROR(G4/G12,"-") -> 99.206349 | H15: =IFERROR(H4/H12,"-") -> 13333.333 | I15: =IFERROR(I4/I12,"-") -> 563.53903 | J15: =IFERROR(J4/J12,"-") -> 99.206349
A16: Horas comerciales | B16: =B7*Supuestos!$C$14+B9*Supuestos!$C$15+B10*Supuestos!$C$16 -> 0.375 | C16: =C7*Supuestos!$C$14+C9*Supuestos!$C$15+C10*Supuestos!$C$16 -> 2.684 | D16: =D7*Supuestos!$C$14+D9*Supuestos!$C$15+D10*Supuestos!$C$16 -> 9.7333333 | E16: =E7*Supuestos!$C$14+E9*Supuestos!$C$15+E10*Supuestos!$C$16 -> 1.5 | F16: =F7*Supuestos!$C$14+F9*Supuestos!$C$15+F10*Supuestos!$C$16 -> 10.736 | G16: =G7*Supuestos!$C$14+G9*Supuestos!$C$15+G10*Supuestos!$C$16 -> 38.933333 | H16: =H7*Supuestos!$C$14+H9*Supuestos!$C$15+H10*Supuestos!$C$16 -> 3 | I16: =I7*Supuestos!$C$14+I9*Supuestos!$C$15+I10*Supuestos!$C$16 -> 21.472 | J16: =J7*Supuestos!$C$14+J9*Supuestos!$C$15+J10*Supuestos!$C$16 -> 77.866667
A17: Coste pruebas no convertidas (€) | B17: =(B11-B12)*Supuestos!$C$33*Supuestos!$C$3 -> 7.5 | C17: =(C11-C12)*Supuestos!$C$33*Supuestos!$C$3 -> 76.05 | D17: =(D11-D12)*Supuestos!$C$33*Supuestos!$C$3 -> 252 | E17: =(E11-E12)*Supuestos!$C$33*Supuestos!$C$3 -> 30 | F17: =(F11-F12)*Supuestos!$C$33*Supuestos!$C$3 -> 304.2 | G17: =(G11-G12)*Supuestos!$C$33*Supuestos!$C$3 -> 1008 | H17: =(H11-H12)*Supuestos!$C$33*Supuestos!$C$3 -> 60 | I17: =(I11-I12)*Supuestos!$C$33*Supuestos!$C$3 -> 608.4 | J17: =(J11-J12)*Supuestos!$C$33*Supuestos!$C$3 -> 2016
A18: CAC completo (€) | B18: =IFERROR((B4+B16*Supuestos!$C$3+B17)/B12,"-") -> 15333.333 | C18: =IFERROR((C4+C16*Supuestos!$C$3+C17)/C12,"-") -> 1294.6182 | D18: =IFERROR((D4+D16*Supuestos!$C$3+D17)/D12,"-") -> 542.32804 | E18: =IFERROR((E4+E16*Supuestos!$C$3+E17)/E12,"-") -> 15333.333 | F18: =IFERROR((F4+F16*Supuestos!$C$3+F17)/F12,"-") -> 1294.6182 | G18: =IFERROR((G4+G16*Supuestos!$C$3+G17)/G12,"-") -> 542.32804 | H18: =IFERROR((H4+H16*Supuestos!$C$3+H17)/H12,"-") -> 15333.333 | I18: =IFERROR((I4+I16*Supuestos!$C$3+I17)/I12,"-") -> 1294.6182 | J18: =IFERROR((J4+J16*Supuestos!$C$3+J17)/J12,"-") -> 542.32804
A19: Contribución N meses de los clientes (€) | B19: =B12*INDEX(Contribucion!$D$4:$D$6,Supuestos!$C$4) -> 28.2 | C19: =C12*INDEX(Contribucion!$D$4:$D$6,Supuestos!$C$4) -> 667.212 | D19: =D12*INDEX(Contribucion!$D$4:$D$6,Supuestos!$C$4) -> 3790.08 | E19: =E12*INDEX(Contribucion!$D$4:$D$6,Supuestos!$C$4) -> 112.8 | F19: =F12*INDEX(Contribucion!$D$4:$D$6,Supuestos!$C$4) -> 2668.848 | G19: =G12*INDEX(Contribucion!$D$4:$D$6,Supuestos!$C$4) -> 15160.32 | H19: =H12*INDEX(Contribucion!$D$4:$D$6,Supuestos!$C$4) -> 225.6 | I19: =I12*INDEX(Contribucion!$D$4:$D$6,Supuestos!$C$4) -> 5337.696 | J19: =J12*INDEX(Contribucion!$D$4:$D$6,Supuestos!$C$4) -> 30320.64
A20: Resultado neto del escenario (€) | B20: =B19-B4-B16*Supuestos!$C$3-B17 -> -86.8 | C20: =C19-C4-C16*Supuestos!$C$3-C17 -> 437.482 | D20: =D19-D4-D16*Supuestos!$C$3-D17 -> 3243.4133 | E20: =E19-E4-E16*Supuestos!$C$3-E17 -> -347.2 | F20: =F19-F4-F16*Supuestos!$C$3-F17 -> 1749.928 | G20: =G19-G4-G16*Supuestos!$C$3-G17 -> 12973.653 | H20: =H19-H4-H16*Supuestos!$C$3-H17 -> -694.4 | I20: =I19-I4-I16*Supuestos!$C$3-I17 -> 3499.856 | J20: =J19-J4-J16*Supuestos!$C$3-J17 -> 25947.307
A23: Valores fraccionarios (p.ej. 0,3 clientes) = esperanza matemática, no un resultado posible. Con volúmenes así de pequeños la varianza domina: ver Umbrales.

Sheet Umbrales
A1: UMBRALES: QUÉ TIENE QUE OCURRIR PARA QUE GOOGLE ADS TENGA SENTIDO
A3: CAC máx. con α del producto activo (€) | C3: =INDEX(Contribucion!$F$4:$F$6,Supuestos!$C$4) -> 1880
A4: Tasa lead→cliente usada (escenario Y) | C4: =Supuestos!D28 -> 0.088725
A5: Coste no publicitario por cliente, escenario Y (€) | C5: =(Embudo!F16*Supuestos!$C$3+Embudo!F17)/Embudo!F12 -> 731.07918 | D5: (horas comerciales + pruebas fallidas por cliente, columna 400 € · Y)
A6: CPL máximo admisible (€) | C6: =MAX(0,(C3-C5)*C4) -> 101.938
A7: Fórmula: CPL máx = (CAC máx α − coste no publicitario por cliente) × tasa lead→cliente
A9: Tabla CPL = CPC / conversión landing (€). Verde si ≤ CPL máximo.
A10: CPC \ CVR | B10: 0.01 | C10: 0.02 | D10: 0.03 | E10: 0.05 | F10: 0.08 | G10: 0.1
A11: 0.75 | B11: =$A11/B$10 -> 75 | C11: =$A11/C$10 -> 37.5 | D11: =$A11/D$10 -> 25 | E11: =$A11/E$10 -> 15 | F11: =$A11/F$10 -> 9.375 | G11: =$A11/G$10 -> 7.5
A12: 1 | B12: =$A12/B$10 -> 100 | C12: =$A12/C$10 -> 50 | D12: =$A12/D$10 -> 33.333333 | E12: =$A12/E$10 -> 20 | F12: =$A12/F$10 -> 12.5 | G12: =$A12/G$10 -> 10
A13: 1.5 | B13: =$A13/B$10 -> 150 | C13: =$A13/C$10 -> 75 | D13: =$A13/D$10 -> 50 | E13: =$A13/E$10 -> 30 | F13: =$A13/F$10 -> 18.75 | G13: =$A13/G$10 -> 15
A14: 2 | B14: =$A14/B$10 -> 200 | C14: =$A14/C$10 -> 100 | D14: =$A14/D$10 -> 66.666667 | E14: =$A14/E$10 -> 40 | F14: =$A14/F$10 -> 25 | G14: =$A14/G$10 -> 20
A15: 2.5 | B15: =$A15/B$10 -> 250 | C15: =$A15/C$10 -> 125 | D15: =$A15/D$10 -> 83.333333 | E15: =$A15/E$10 -> 50 | F15: =$A15/F$10 -> 31.25 | G15: =$A15/G$10 -> 25
A16: 3 | B16: =$A16/B$10 -> 300 | C16: =$A16/C$10 -> 150 | D16: =$A16/D$10 -> 100 | E16: =$A16/E$10 -> 60 | F16: =$A16/F$10 -> 37.5 | G16: =$A16/G$10 -> 30
A17: 4 | B17: =$A17/B$10 -> 400 | C17: =$A17/C$10 -> 200 | D17: =$A17/D$10 -> 133.33333 | E17: =$A17/E$10 -> 80 | F17: =$A17/F$10 -> 50 | G17: =$A17/G$10 -> 40
A18: 5 | B18: =$A18/B$10 -> 500 | C18: =$A18/C$10 -> 250 | D18: =$A18/D$10 -> 166.66667 | E18: =$A18/E$10 -> 100 | F18: =$A18/F$10 -> 62.5 | G18: =$A18/G$10 -> 50
A19: 6 | B19: =$A19/B$10 -> 600 | C19: =$A19/C$10 -> 300 | D19: =$A19/D$10 -> 200 | E19: =$A19/E$10 -> 120 | F19: =$A19/F$10 -> 75 | G19: =$A19/G$10 -> 60
A21: Tamaño de muestra: con conversión real del 5 %, P(0 leads) = 0,95^clics → 20 clics: 36 % · 40 clics: 13 % · 100 clics: 0,6 %.
A22: Para estimar una conversión ~5 % con ±2,5 puntos (IC 95 %) hacen falta ≈ 292 clics: n = 1,96² · p(1−p) / 0,025².
A23: Clics necesarios (fórmula, p y margen editables):
B24: p | C24: 0.05
B25: margen ± | C25: 0.025
B26: n | C26: =ROUNDUP(1.96^2*C24*(1-C24)/C25^2,0) -> 292

Sheet Oferta400
A1: OFERTA PROMOCIONAL — CÁLCULO DE CAJA
A3: Gasto mínimo exigido sin impuestos (€) | B3: 400 | C3: [A VERIFICAR EN LA CUENTA] Los términos oficiales dicen 'requisito de inversión mínima de la oferta seleccionada' sin cifra; terceros (clicksem.es 07/2026, ongoing.es 12/2025) citan gastar 400 € → 400 €
A4: Crédito recibido (€) | B4: 400 | C4: [FUENTE] texto de la oferta mostrada al usuario
A5: Plazo para alcanzar el gasto (días) | B5: 60 | C5: [FUENTE] google.com/intl/es_es/ads/coupons/terms/cyoi/
A6: Días hasta abono del crédito (típico) | B6: 35 | C6: [FUENTE] ídem: 'por lo general en un plazo de 35 días'
A7: Caducidad del crédito tras aplicarse (días) | B7: 60 | C7: [FUENTE] ídem
A8: Recargo operativo regulatorio España | B8: 0.03 | C8: [FUENTE] support.google.com/google-ads/answer/9750227 — desde 01/07/2024. Si cuenta o no para el umbral: NO VERIFICADO
A10: Desembolso propio mínimo para desbloquear (€, con recargo, sin IVA) | B10: =B3*(1+B8) -> 412
A11: Gasto total si se consume también el crédito (€ de inversión publicitaria) | B11: =B3+B4 -> 800
A12: Recargo sobre el tramo pagado con crédito (€, NO VERIFICADO si lo cubre el crédito) | B12: =B4*B8 -> 12
A13: Coste efectivo por € de anuncio si se usa todo (propio / total) | B13: =(B10+B12)/B11 -> 0.53
A14: Ventana total aproximada de la promoción (días) | B14: =B5+B6+B7 -> 155
A16: Lectura: los 400 € no son gratis. Primero hay que pagar el gasto mínimo en 60 días; el crédito llega después y caduca. Solo compensa si el gasto propio ya se iba a hacer con criterio de aprendizaje.
